ignacio_bot/__init__.py
ignacio_bot/app.py
ignacio_bot/system_context.txt
ignacio_bot/static/GRG_logo.png
ignacio_bot/templates/index.html
ignacio_bot-0.9.2.dist-info/LICENSE
ignacio_bot-0.9.2.dist-info/METADATA
ignacio_bot-0.9.2.dist-info/WHEEL
ignacio_bot-0.9.2.dist-info/entry_points.txt
ignacio_bot-0.9.2.dist-info/top_level.txt
ignacio_bot-0.9.2.dist-info/RECORD
