Metadata-Version: 2.1
Name: ignacio-bot
Version: 0.9.2
Summary: A simple Flask app that lets you talk to a custom bot.
Home-page: https://github.com/arpanseth/ignacio_bot
Author: Arpan Seth
Author-email: aseth42@gmail.com
Project-URL: Source, https://github.com/arpanseth/ignacio_bot
Classifier: Programming Language :: Python :: 3
Classifier: License :: OSI Approved :: MIT License
Classifier: Operating System :: OS Independent
Requires-Python: >=3.11
License-File: LICENSE
Requires-Dist: Flask
Requires-Dist: openai
Requires-Dist: flask-session
